code2postman_mcp/__init__.py
code2postman_mcp/server.py
code2postman_mcp/consts/__init__.py
code2postman_mcp/consts/excluded_files.py
code2postman_mcp/consts/postman_template.py
code2postman_mcp/tools/__init__.py
code2postman_mcp/tools/handle_files.py
code2postman_mcp/tools/handle_postman.py
code2postman_mcp/utils/__init__.py
code2postman_mcp/utils/files.py
code2postman_mcp-0.1.2.dist-info/METADATA
code2postman_mcp-0.1.2.dist-info/WHEEL
code2postman_mcp-0.1.2.dist-info/entry_points.txt
code2postman_mcp-0.1.2.dist-info/top_level.txt
code2postman_mcp-0.1.2.dist-info/RECORD
